thousandrooms/__init__.py
thousandrooms/__main__.py
thousandrooms/creature.py
thousandrooms/door.py
thousandrooms/game.py
thousandrooms/item.py
thousandrooms/item_list.py
thousandrooms/maps.py
thousandrooms/monster.py
thousandrooms/monster_list.py
thousandrooms/player.py
thousandrooms/room.py
thousandrooms/room_list.py
thousandrooms/store.py
thousandrooms/utils.py
thousandrooms-0.1.9.dist-info/LICENSE
thousandrooms-0.1.9.dist-info/METADATA
thousandrooms-0.1.9.dist-info/WHEEL
thousandrooms-0.1.9.dist-info/entry_points.txt
thousandrooms-0.1.9.dist-info/top_level.txt
thousandrooms-0.1.9.dist-info/RECORD
