Metadata-Version: 2.1
Name: thousandrooms
Version: 0.1.9
Summary: A simple roguelike RPG
Home-page: https://github.com/bypung/thousandrooms
Author: Ben Pung
Author-email: ben@houseofpung.net
Classifier: Programming Language :: Python :: 3
Classifier: License :: OSI Approved :: MIT License
Classifier: Operating System :: OS Independent
License-File: LICENSE
Requires-Dist: colored
Requires-Dist: colorama
Requires-Dist: dill
